bstrap/__init__.py
bstrap/examples.py
bstrap-0.0.8.dist-info/LICENSE
bstrap-0.0.8.dist-info/METADATA
bstrap-0.0.8.dist-info/WHEEL
bstrap-0.0.8.dist-info/top_level.txt
bstrap-0.0.8.dist-info/RECORD
