Metadata-Version: 2.1
Name: bstrap
Version: 0.0.8
Summary: A package to perform hypothesis testing and compute confidence intervals using bootstrapping.
Home-page: https://github.com/fpgdubost/bstrap
Author: Florian Dubost
Author-email: floriandubost1@gmail.com
License: UNKNOWN
Project-URL: Bug Tracker, https://github.com/fpgdubost/bstrap/issues
Platform: UNKNOWN
Classifier: Programming Language :: Python :: 3
Classifier: License :: OSI Approved :: MIT License
Classifier: Operating System :: OS Independent
Requires-Python: >=3.6
License-File: LICENSE
